{
  "PROCESSING": {
    "PAIR": "C:EURCHF",
    "INTERVAL": 5,
    "START_DATE": "2010-01-01",
    "STEPS_IN": 96,
    "STEPS_OUT": 48,
    "OVERLAP": 48,
    "TEST_LENGTH": 120,
    "EPOCHS": 1000,
    "BATCH_SIZE": 8,
    "LEARNING_RATE": 0.0001,
    "VALIDATION_SPLIT": 0.01,
    "PATIENCE": 100,
    "PATIENCE_LR_SCHEDULE": 25,
    "TARGET_FEATURE": "c"
  },
  "BRANCHES": {
    "C:EURCHF": {
      "INDICATORS": ["MA5", "MA25"],
      "NODES": {
        "TRANSFORMER": [96, 96],
        "LSTM": [96, 96],
        "DENSE": [192, 192],
        "ATTENTION_HEADS": [64, 64],
        "DROPOUT": [0.2, 0.2]
      }
    }
  },
  "MAIN_BRANCH": {
    "NODES": {
      "TRANSFORMER": [4, 24],
      "LSTM": [24, 24],
      "DENSE": [48, 48],
      "ATTENTION_HEADS": [64, 64],
      "DROPOUT": [0.0, 0.0]
    }
  },
  "OUTPUT": {
    "NODES": {
      "DENSE": [48, 48],
      "DROPOUT": [0.0, 0.0]
    }
  }
}
